denormalized-0.0.13.dist-info/METADATA
denormalized-0.0.13.dist-info/WHEEL
denormalized/datafusion/catalog.py
denormalized/datafusion/functions.py
denormalized/datafusion/record_batch.py
denormalized/datafusion/input/__init__.py
denormalized/datafusion/input/location.py
denormalized/datafusion/input/base.py
denormalized/datafusion/dataframe.py
denormalized/datafusion/__init__.py
denormalized/datafusion/context.py
denormalized/datafusion/common.py
denormalized/datafusion/py.typed
denormalized/datafusion/udf.py
denormalized/datafusion/expr.py
denormalized/datafusion/object_store.py
denormalized/__init__.py
denormalized/data_stream.py
denormalized/feast_data_stream.py
denormalized/context.py
denormalized/utils.py
denormalized/feast_data_stream.pyi
denormalized/_d_internal.abi3.so
denormalized-0.0.13.dist-info/RECORD
