Metadata-Version: 2.3
Name: denormalized
Version: 0.0.13
Requires-Dist: pyarrow >=17.0.0
Requires-Dist: datafusion >=40.1.0
Requires-Dist: pip >=24.3.1
Requires-Dist: feast ; extra == 'feast'
Provides-Extra: feast
Summary: Embeddable stream processing engine
Home-Page: https://github.com/probably-nothing-labs/denormalized.git
Requires-Python: >=3.12
Project-URL: Source Code, https://github.com/probably-nothing-labs/denormalized.git
